.flake8
AUTHORS
ChangeLog
LICENSE
README.rst
requirements.txt
setup.cfg
setup.py
data/20205.js
data/20404.js
data/20601.js
data/20810.js
data/21401.js
data/21670.js
data/21910.js
data/22005.js
data/22210.js
data/22601.js
data/22801.js
data/23003.js
data/23201.js
data/23402.js
data/23415.js
data/23801.js
data/2380171.js
data/2380172.js
data/24405.js
data/24602.js
data/24705.js
data/24802.js
data/26202.js
data/26209.js
data/26801.js
data/27077.js
data/27201.js
data/27402.js
data/27602.js
data/27801.js
data/28001.js
data/28401.js
data/28602.js
data/2860251.js
data/28802.js
data/29340.js
data/29403.js
data/40004.js
data/40401.js
data/40405.js
data/40411.js
data/40413.js
data/40415.js
data/40420.js
data/40427.js
data/40430.js
data/40443.js
data/40446.js
data/40460.js
data/40484.js
data/40488.js
data/40566.js
data/40567.js
data/405750.js
data/405751.js
data/405752.js
data/405753.js
data/405754.js
data/405755.js
data/405756.js
data/41302.js
data/42403.js
data/42602.js
data/42702.js
data/45406.js
data/46692.js
data/50213.js
data/50219.js
data/50503.js
data/50506.js
data/52503.js
data/53001.js
data/54201.js
data/60202.js
data/62002.js
data/63001.js
data/64004.js
data/64304.js
data/64710.js
data/65101.js
data/65501.js
data/72418.js
data/73001.js
data/JsIncludesRepo.js
data/WebUIProductName.js
data/allpages-min.js
data/allwebui-min.js
data/en-gb.js
data/get-urls.sh
data/home.htm
data/index.html
data/launch.js
data/log4javascript.js
data/urls
data/vendor.js
data/vendorWifi.js
data/webuiconfig.js
docs/Makefile
docs/conf.py
docs/docs.sh
docs/index.rst
docs/make.bat
docs/source/modules.rst
docs/source/vodem.api.rst
docs/source/vodem.connection.rst
docs/source/vodem.exceptions.rst
docs/source/vodem.rst
docs/source/vodem.simple.rst
docs/source/vodem.util.rst
examples/debug.py
examples/loop.py
test/__init__.py
test/unit/__init__.py
test/unit/api/__init__.py
test/unit/api/test_account_type.py
test/unit/api/test_activate_flag.py
test/unit/api/test_apn_config.py
vodem_vodafone_K4607_Z.egg-info/PKG-INFO
vodem_vodafone_K4607_Z.egg-info/SOURCES.txt
vodem_vodafone_K4607_Z.egg-info/dependency_links.txt
vodem_vodafone_K4607_Z.egg-info/not-zip-safe
vodem_vodafone_K4607_Z.egg-info/pbr.json
vodem_vodafone_K4607_Z.egg-info/requires.txt
vodem_vodafone_K4607_Z.egg-info/top_level.txt