Metadata-Version: 1.1
Name: vodem-vodafone-K4607-Z
Version: 0.3.0
Summary: Vodafone Vodafone K4607-Z web interface python bindings
Home-page: http://pypi.python.org/pypi/vodem-vodafone-K4607-Z
Author: alzeih
Author-email: alzeih@users.noreply.github.com
License: UNKNOWN
Platform: UNKNOWN
Classifier: Development Status :: 3 - Alpha
Classifier: Operating System :: OS Independent
Classifier: License :: OSI Approved :: MIT License
Classifier: Topic :: Communications :: Telephony
Classifier: Programming Language :: Python
Classifier: Programming Language :: Python :: 3 :: Only
Classifier: Programming Language :: Python :: 3.5
